{"inkVersion":21,"root":[[{"->":"main"},["done",{"#f":5,"#n":"g-0"}],null],"done",{"main":["#","^leftPortrait:wizard","/#","#","^rightPortrait:maid","/#","^Oh my gosh! ","#","^speaker:Maid ","/#","#","^layout:right","/#","\n","^Oh good heavens!!","\n","^Oh goodness gracious!!!","\n","^Is it safe? Is she gone?","\n","^Calm down! ","#","^speaker:Wizard ","/#","#","^layout:left","/#","\n","^What are you talking about?","\n","^Someone... ","#","^speaker:Maid","/#","#","^layout:right","/#","\n","^Someone!!","\n","^... ","#","^speaker:Wizard ","/#","#","^layout:left","/#","\n","^Someone broke in... ","#","^speaker:Maid ","/#","#","^layout:right","/#","\n","^I was cleaning the floors, when I heard dreadful commotion from downstairs.","\n","^Then, suddenly, these lasers turned on, trapping me!","\n","^And then I heard a hideous sound...","\n","^Laughter!","\n","^A woman's laughter...","\n","^Then, she walked up the stairs, and...","\n","^OH GOD!","\n","^Chillax, name. ","#","^speaker:Wizard","/#","#","^layout:left","/#","\n","^Did you see what she looked like?","\n","^N-no... ","#","^speaker:Maid","/#","#","^layout:right","/#","\n","^To be quite hoenst, I was so frightened that I covered my eyes.","\n","^But I heard her move upstairs.","\n","^You must find this horrid wench! For our safety!","\n","^Right on it, name. ","#","^speaker:Wizard","/#","#","^layout:left","/#","\n","end",{"#f":1}],"#f":1}],"listDefs":{}}